facelooker/__init__.py
facelooker/helpers.py
facelooker/models.py
facelooker/motion.py
facelooker/pose.py
facelooker/strategy.py
facelooker-0.1.0.dist-info/METADATA
facelooker-0.1.0.dist-info/WHEEL
facelooker-0.1.0.dist-info/licenses/LICENSE
facelooker-0.1.0.dist-info/RECORD
