Metadata-Version: 2.4
Name: facelooker
Version: 0.1.0
Summary: A tiny library to make the face landmarks detection easier.
Project-URL: Homepage, https://github.com/abdielsouza/facelooker
Project-URL: Repository, https://github.com/abdielsouza/facelooker
Author-email: Abdiel Souza <abdielcsouza@gmail.com>
License-File: LICENSE
Requires-Python: >=3.10
Requires-Dist: numpy
Requires-Dist: opencv-python
Provides-Extra: dev
Requires-Dist: black; extra == 'dev'
Requires-Dist: flake8; extra == 'dev'
Requires-Dist: pytest; extra == 'dev'
